taurunner/Casino.py
taurunner/__init__.py
taurunner/main.py
taurunner/body/__init__.py
taurunner/body/body.py
taurunner/body/earth.py
taurunner/body/sun.py
taurunner/cross_sections/__init__.py
taurunner/cross_sections/xs.py
taurunner/cross_sections/xs_model.py
taurunner/particle/__init__.py
taurunner/particle/particle.py
taurunner/particle/utils.py
taurunner/resources/__init__.py
taurunner/resources/column_depth_splines/__init__.py
taurunner/resources/cross_section_tables/CC_table.npy
taurunner/resources/cross_section_tables/CC_table_py3.npy
taurunner/resources/cross_section_tables/CSMS_nu_n_dsde_CC.pkl
taurunner/resources/cross_section_tables/CSMS_nu_n_dsde_NC.pkl
taurunner/resources/cross_section_tables/CSMS_nu_n_sigma_CC.pkl
taurunner/resources/cross_section_tables/CSMS_nu_n_sigma_NC.pkl
taurunner/resources/cross_section_tables/CSMS_nu_p_dsde_CC.pkl
taurunner/resources/cross_section_tables/CSMS_nu_p_dsde_NC.pkl
taurunner/resources/cross_section_tables/CSMS_nu_p_sigma_CC.pkl
taurunner/resources/cross_section_tables/CSMS_nu_p_sigma_NC.pkl
taurunner/resources/cross_section_tables/CSMS_nubar_n_dsde_CC.pkl
taurunner/resources/cross_section_tables/CSMS_nubar_n_dsde_NC.pkl
taurunner/resources/cross_section_tables/CSMS_nubar_n_sigma_CC.pkl
taurunner/resources/cross_section_tables/CSMS_nubar_n_sigma_NC.pkl
taurunner/resources/cross_section_tables/CSMS_nubar_p_dsde_CC.pkl
taurunner/resources/cross_section_tables/CSMS_nubar_p_dsde_NC.pkl
taurunner/resources/cross_section_tables/CSMS_nubar_p_sigma_CC.pkl
taurunner/resources/cross_section_tables/CSMS_nubar_p_sigma_NC.pkl
taurunner/resources/cross_section_tables/NC_table.npy
taurunner/resources/cross_section_tables/NC_table_py3.npy
taurunner/resources/cross_section_tables/__init__.py
taurunner/resources/cross_section_tables/dipole_nu_n_dsde_CC.pkl
taurunner/resources/cross_section_tables/dipole_nu_n_dsde_NC.pkl
taurunner/resources/cross_section_tables/dipole_nu_n_sigma_CC.pkl
taurunner-1.0.0.dist-info/LICENSE
taurunner-1.0.0.dist-info/METADATA
taurunner-1.0.0.dist-info/WHEEL
taurunner-1.0.0.dist-info/top_level.txt
taurunner-1.0.0.dist-info/RECORD
