Metadata-Version: 2.1
Name: taurunner
Version: 1.0.0
Summary: Code for propagating ultra-high-energy neutrinos
Home-page: https://github.com/icecube/TauRunner
Author: Safa, I. et al.
Author-email: isafa@wisc.edu
License: UNKNOWN
Platform: UNKNOWN
Classifier: Programming Language :: Python :: 3
Classifier: License :: OSI Approved :: MIT License
Requires-Python: >=3.1
License-File: LICENSE
Requires-Dist: numpy (>=1.16.6)
Requires-Dist: scipy (>=1.2.3)
Requires-Dist: proposal (==6.1.6)
